AminoLightBots/__init__.py
AminoLightBots/bot.py
AminoLightBots/custom_filters.py
AminoLightBots/handler_backends.py
AminoLightBots/typing.py
AminoLightBots/util.py
amino_light_bots-0.0.8.dist-info/METADATA
amino_light_bots-0.0.8.dist-info/WHEEL
amino_light_bots-0.0.8.dist-info/top_level.txt
amino_light_bots-0.0.8.dist-info/RECORD
